{
  "centrals": [
    {
      "id": "79d4",
      "name": "Central 1",
      "mac": "12:34:45:67:89:83",
      "modelId": "2"
    },
    {
      "id": "79d4",
      "name": "Central 2",
      "mac": "12:34:45:67:89:83",
      "modelId": "3"
    },
    {
      "id": "79d4",
      "name": "Central 3",
      "mac": "12:34:45:67:89:83",
      "modelId": "4"
    },
    {
      "id": "79d4",
      "name": "Central 4",
      "mac": "12:34:45:67:89:83",
      "modelId": "5"
    },
    {
      "id": "79d4",
      "name": "Central 5",
      "mac": "12:34:45:67:89:83",
      "modelId": "1"
    },
    {
      "id": "79d4",
      "name": "Central 6",
      "mac": "12:34:45:67:89:83",
      "modelId": "2"
    },
    {
      "id": "79d4",
      "name": "Central 7",
      "mac": "12:34:45:67:89:83",
      "modelId": "3"
    },
    {
      "id": "acbc",
      "name": "Central 8",
      "mac": "67:86:95:78:35:63",
      "modelId": "6"
    },
    {
      "id": "3fef",
      "name": "Central 9",
      "mac": "34:32:34:13:43:41",
      "modelId": "2"
    }
  ],
  "models": [
    {
      "id": "1",
      "name": "AMT 4010"
    },
    {
      "id": "2",
      "name": "AMT 4010 SMART"
    },
    {
      "id": "3",
      "name": "AMT 2018"
    },
    {
      "id": "4",
      "name": "AMT 2018 E/EG"
    },
    {
      "id": "5",
      "name": "AMT 1000"
    },
    {
      "id": "6",
      "name": "AMT 8000"
    }
  ]
}
